{"cameraMode":{"drawMode":0,"name":"Shaded","section":"Shading Mode"},"sceneLighting":false,"audioPlay":false,"sceneViewState":{"m_AlwaysRefresh":false,"showFog":true,"showSkybox":false,"showFlares":true,"showImageEffects":true,"showParticleSystems":true,"showVisualEffectGraphs":true,"m_FxEnabled":true},"in2DMode":false,"pivot":{"x":1.9409430027008057,"y":2.732450485229492,"z":-138.2339630126953},"rotation":{"x":0.1466331034898758,"y":-0.8526909947395325,"z":0.33565548062324526,"w":0.37252897024154665},"size":7.936343193054199,"orthographic":false}